haywire/__init__.py
haywire/haywire.py
haywire-0.1.1.dist-info/LICENSE
haywire-0.1.1.dist-info/METADATA
haywire-0.1.1.dist-info/WHEEL
haywire-0.1.1.dist-info/top_level.txt
haywire-0.1.1.dist-info/RECORD
